flit/__init__.py
flit/__main__.py
flit/_get_dirs.py
flit/build.py
flit/buildapi.py
flit/config.py
flit/init.py
flit/install.py
flit/log.py
flit/logo.py
flit/sdist.py
flit/tomlify.py
flit/upload.py
flit/validate.py
flit/wheel.py
flit/license_templates/apache
flit/license_templates/gpl3
flit/license_templates/mit
flit/vcs/__init__.py
flit/vcs/git.py
flit/vcs/hg.py
flit/vendorized/__init__.py
flit/vendorized/readme/__init__.py
flit/vendorized/readme/clean.py
flit/vendorized/readme/rst.py
flit-3.11.0.dist-info/entry_points.txt
flit-3.11.0.dist-info/licenses/LICENSE
flit-3.11.0.dist-info/WHEEL
flit-3.11.0.dist-info/METADATA
flit-3.11.0.dist-info/RECORD
