Metadata-Version: 2.4
Name: flit
Version: 3.11.0
Summary: A simple packaging tool for simple packages.
Author-email: Thomas Kluyver <thomas@kluyver.me.uk>
Requires-Python: >=3.8
License-Expression: BSD-3-Clause
Classifier: Intended Audience :: Developers
Classifier: Programming Language :: Python :: 3
Classifier: Topic :: Software Development :: Libraries :: Python Modules
License-File: LICENSE
Requires-Dist: flit_core >=3.11.0
Requires-Dist: requests
Requires-Dist: docutils
Requires-Dist: tomli-w
Requires-Dist: pip
Requires-Dist: sphinx ; extra == "doc"
Requires-Dist: sphinxcontrib_github_alt ; extra == "doc"
Requires-Dist: pygments-github-lexers ; extra == "doc"
Requires-Dist: testpath ; extra == "test"
Requires-Dist: responses ; extra == "test"
Requires-Dist: pytest>=2.7.3 ; extra == "test"
Requires-Dist: pytest-cov ; extra == "test"
Requires-Dist: tomli ; extra == "test"
Project-URL: Changelog, https://flit.pypa.io/en/stable/history.html
Project-URL: Documentation, https://flit.pypa.io
Project-URL: Source, https://github.com/pypa/flit
Provides-Extra: doc
Provides-Extra: test
